LICENSE.txt
MANIFEST.in
README.md
README.rst
setup.py
fynance/__init__.py
fynance/_exceptions.py
fynance/_wrappers.py
fynance/version.py
fynance.egg-info/PKG-INFO
fynance.egg-info/SOURCES.txt
fynance.egg-info/dependency_links.txt
fynance.egg-info/requires.txt
fynance.egg-info/top_level.txt
fynance/algorithms/__init__.py
fynance/algorithms/allocation.py
fynance/algorithms/browsers.py
fynance/algorithms/browsers_cy.c
fynance/algorithms/browsers_cy.cpython-37m-x86_64-linux-gnu.so
fynance/algorithms/browsers_cy.cpython-39-x86_64-linux-gnu.so
fynance/algorithms/browsers_cy.pyx
fynance/algorithms/rolling.py
fynance/backtest/__init__.py
fynance/backtest/_basis_plot.py
fynance/backtest/analysis.py
fynance/backtest/dynamic_plot_backtest.py
fynance/backtest/loss.py
fynance/backtest/plot.py
fynance/backtest/plot_backtest.py
fynance/backtest/plot_tools.py
fynance/backtest/print_stats.py
fynance/dev/.ipynb
fynance/dev/Kalman_Filter.ipynb
fynance/dev/Untitled.ipynb
fynance/dev/__init__.py
fynance/dev/example_kalman_filter.py
fynance/dev/optim_time_period.ipynb
fynance/dev/optim_time_period.py
fynance/dev/plot_backtest2.py
fynance/dev/roll_min_max.ipynb
fynance/dev/roll_neural_network2.py
fynance/dev/series.py
fynance/dev/set_neuralnetwork_tools.py
fynance/dev/test_backtest.ipynb
fynance/dev/test_browser_data.ipynb
fynance/dev/test_fig_plot.ipynb
fynance/dev/test_optim_time_period.py
fynance/dev/test_roll_NN_test.ipynb
fynance/dev/test_roll_NN_v01.ipynb
fynance/dev/test_roll_NN_v01_speed_test.ipynb
fynance/dev/test_timeit_functions.ipynb
fynance/dev/.ipynb_checkpoints/.ipynb-checkpoint
fynance/dev/.ipynb_checkpoints/Kalman_Filter-checkpoint.ipynb
fynance/dev/.ipynb_checkpoints/Untitled-checkpoint.ipynb
fynance/dev/.ipynb_checkpoints/optim_time_period-checkpoint.ipynb
fynance/dev/.ipynb_checkpoints/roll_min_max-checkpoint.ipynb
fynance/dev/.ipynb_checkpoints/test_backtest-checkpoint.ipynb
fynance/dev/.ipynb_checkpoints/test_browser_data-checkpoint.ipynb
fynance/dev/.ipynb_checkpoints/test_fig_plot-checkpoint.ipynb
fynance/dev/.ipynb_checkpoints/test_roll_NN_test-checkpoint.ipynb
