Metadata-Version: 1.2
Name: fynance
Version: 1.1.0
Summary: Python and Cython scripts of machine learning, econometrics and statistical features for financial analysis [In progress]
Home-page: https://github.com/ArthurBernard/Fynance
Author: ['Arthur Bernard']
Author-email: arthur.bernard.92@gmail.com
License: MIT
Download-URL: https://pypi.org/project/fynance/
Project-URL: Documentation, https://fynance.readthedocs.io/
Project-URL: Source Code, https://github.com/ArthurBernard/Fynance/
Platform: UNKNOWN
Classifier: Development Status :: 4 - Beta
Classifier: Intended Audience :: Financial and Insurance Industry
Classifier: Intended Audience :: Science/Research
Classifier: License :: OSI Approved :: MIT License
Classifier: Operating System :: POSIX :: Linux
Classifier: Programming Language :: Python
Classifier: Programming Language :: Cython
Classifier: Programming Language :: Python :: 3
Classifier: Programming Language :: Python :: 3.6
Classifier: Programming Language :: Python :: 3.7
Classifier: Programming Language :: Python :: 3.8
Classifier: Topic :: Office/Business :: Financial
Classifier: Topic :: Scientific/Engineering :: Artificial Intelligence
